setup.py
AASMessenger_Server.egg-info/PKG-INFO
AASMessenger_Server.egg-info/SOURCES.txt
AASMessenger_Server.egg-info/dependency_links.txt
AASMessenger_Server.egg-info/requires.txt
AASMessenger_Server.egg-info/top_level.txt
server/__init__.py
server/server.py
server/setup_server.py
server/common/__init__.py
server/common/decos.py
server/common/descriptors.py
server/common/errors.py
server/common/metaclasses.py
server/common/settings.py
server/common/utils.py
server/log/__init__.py
server/log/client_log_config.py
server/log/server_log_config.py
server/server/__init__.py
server/server/add_user.py
server/server/config_window.py
server/server/core.py
server/server/database.py
server/server/main_window.py
server/server/remove_user.py
server/server/stat_window.py
server/unit_tests/__init__.py