Metadata-Version: 1.0
Name: AASMessenger-Server
Version: 1.0.1
Summary: Messenger_Server
Home-page: UNKNOWN
Author: Anton Sobolev
Author-email: antony.sobolev@gmail.com
License: UNKNOWN
Platform: UNKNOWN
